tailli/__init__.py
tailli/client.py
tailli/exceptions.py
tailli/models.py
tailli/utils.py
tailli-0.2.0.dist-info/METADATA
tailli-0.2.0.dist-info/WHEEL
tailli-0.2.0.dist-info/licenses/LICENSE
tailli-0.2.0.dist-info/RECORD
